{
  "todos": [
    {
      "id": 8047,
      "text": "Ojas",
      "isComplete": false,
      "createdAt": "2024-08-04T12:13:25.170Z",
      "lastUpdate": "2024-08-04T12:13:25.170Z",
      "removedAt": null
    },
    {
      "id": 1761,
      "text": "wkjs1n",
      "isComplete": false,
      "createdAt": "2024-08-04T12:13:34.557Z",
      "lastUpdate": "2024-08-04T12:13:34.557Z",
      "removedAt": null
    },
    {
      "id": 3077,
      "text": "wdkjbw",
      "isComplete": false,
      "createdAt": "2024-08-04T12:13:35.206Z",
      "lastUpdate": "2024-08-04T12:13:35.206Z",
      "removedAt": null
    },
    {
      "id": 7659,
      "text": "wdkjw",
      "isComplete": false,
      "createdAt": "2024-08-04T12:13:35.834Z",
      "lastUpdate": "2024-08-04T12:13:35.834Z",
      "removedAt": null
    }
  ]
}